parallels/__init__.py
parallels/concurrent.py
parallels/dask_.py
parallels/executor.py
parallels/futures.py
parallels/ray_.py
parallels-0.1.0.dist-info/LICENSE
parallels-0.1.0.dist-info/METADATA
parallels-0.1.0.dist-info/WHEEL
parallels-0.1.0.dist-info/top_level.txt
parallels-0.1.0.dist-info/RECORD
