Metadata-Version: 2.1
Name: parallels
Version: 0.1.0
Summary: An asyncio API that mimics concurrent.futures, with support for task-graph executors
Home-page: https://github.com/agoose77/parallels
Author: Angus Hollands
Author-email: goosey15@gmail.com
License: BSD-3-Clause
Project-URL: Bug Tracker, https://github.com/agoose77/parallels/issues
Keywords: literate-programming,literary,notebook,dask,ray,parallel,concurrent-futures,executor
Platform: Any
Classifier: Development Status :: 4 - Beta
Classifier: Intended Audience :: Developers
Classifier: Intended Audience :: Science/Research
Classifier: License :: OSI Approved :: BSD License
Classifier: Operating System :: OS Independent
Classifier: Programming Language :: Python
Classifier: Programming Language :: Python :: 3
Classifier: Programming Language :: Python :: 3 :: Only
Classifier: Programming Language :: Python :: 3.8
Classifier: Programming Language :: Python :: 3.9
Requires-Python: >=3.8
